Odyssey/__init__.py
Odyssey/db_conf.py
Odyssey/file_utils.py
Odyssey/handler.py
Odyssey/interface.py
Odyssey/odyssey.py
OdysseyDB-1.1.0.dist-info/METADATA
OdysseyDB-1.1.0.dist-info/RECORD
OdysseyDB-1.1.0.dist-info/WHEEL
OdysseyDB-1.1.0.dist-info/top_level.txt
