Metadata-Version: 2.1
Name: OdysseyDB
Version: 1.1.0
Summary: A lightweight migratable file based key-value database with redis-like api and more features.
Home-page: https://github.com/Eathoublu/OdysseyDB
Author: Yixiao Lan
Author-email: yixiaolan@foxmail.com
License: UNKNOWN
Platform: UNKNOWN
Classifier: Programming Language :: Python :: 3
Classifier: License :: OSI Approved :: Mozilla Public License 2.0 (MPL 2.0)
Classifier: Operating System :: OS Independent
Requires-Python: >=3.0
